pytwitcherapi/__init__.py
pytwitcherapi/constants.py
pytwitcherapi/exceptions.py
pytwitcherapi/models.py
pytwitcherapi/oauth.py
pytwitcherapi/session.py
pytwitcherapi/chat/__init__.py
pytwitcherapi/chat/client.py
pytwitcherapi/chat/connection.py
pytwitcherapi/chat/message.py
pytwitcherapi/html/extract_token_site.html
pytwitcherapi/html/success_site.html
pytwitcherapi-0.9.3.dist-info/DESCRIPTION.rst
pytwitcherapi-0.9.3.dist-info/METADATA
pytwitcherapi-0.9.3.dist-info/RECORD
pytwitcherapi-0.9.3.dist-info/WHEEL
pytwitcherapi-0.9.3.dist-info/metadata.json
pytwitcherapi-0.9.3.dist-info/top_level.txt
