Metadata-Version: 2.0
Name: pytwitcherapi
Version: 0.9.3
Summary: Python API for interacting with twitch.tv
Home-page: https://github.com/Pytwitcher/pytwitcherapi
Author: David Zuber
Author-email: zuber.david@gmx.de
License: BSD
Keywords: pytwitcherapi
Platform: UNKNOWN
Classifier: Development Status :: 4 - Beta
Classifier: Intended Audience :: End Users/Desktop
Classifier: License :: OSI Approved :: BSD License
Classifier: Natural Language :: English
Classifier: Programming Language :: Python :: 2
Classifier: Programming Language :: Python :: 2.7
Classifier: Programming Language :: Python :: 3
Classifier: Programming Language :: Python :: 3.3
Classifier: Programming Language :: Python :: 3.4
Classifier: Operating System :: OS Independent
Requires-Dist: irc (>=15)
Requires-Dist: m3u8
Requires-Dist: oauthlib
Requires-Dist: requests
Requires-Dist: requests-oauthlib
